{
    "time": "25.09.2021 10:00",
    "home": "Watford",
    "away": "Newcastle",
    "placar": "1-1",
    "placarHafHome": "0",
    "placarHafAway": "1",
    "oddsHome": "2.05",
    "oddsDraw": "3.50",
    "oddsAway": "3.50",
    "homeGols": [
        "72'"
    ],
    "awayGols": [
        "23'"
    ],
    "allgols": [
        "23'",
        "72'"
    ],
    "halfStats": [
        {
            "categoria": "Posse de bola",
            "home": "49%",
            "away": "51%"
        },
        {
            "categoria": "Tentativas de gol",
            "home": "6",
            "away": "11"
        },
        {
            "categoria": "Finalizações",
            "home": "2",
            "away": "2"
        },
        {
            "categoria": "Chutes fora",
            "home": "2",
            "away": "4"
        },
        {
            "categoria": "Chutes bloqueados",
            "home": "2",
            "away": "5"
        },
        {
            "categoria": "Faltas cobradas",
            "home": "8",
            "away": "9"
        },
        {
            "categoria": "Escanteios",
            "home": "2",
            "away": "5"
        },
        {
            "categoria": "Impedimentos",
            "home": "0",
            "away": "1"
        },
        {
            "categoria": "Laterais cobrados",
            "home": "12",
            "away": "10"
        },
        {
            "categoria": "Defesas do goleiro",
            "home": "1",
            "away": "2"
        },
        {
            "categoria": "Faltas",
            "home": "9",
            "away": "8"
        },
        {
            "categoria": "Cartões amarelos",
            "home": "2",
            "away": "2"
        },
        {
            "categoria": "Total de passes",
            "home": "172",
            "away": "172"
        },
        {
            "categoria": "Passes completados",
            "home": "136",
            "away": "139"
        },
        {
            "categoria": "Desarmes",
            "home": "7",
            "away": "10"
        },
        {
            "categoria": "Ataques",
            "home": "55",
            "away": "51"
        },
        {
            "categoria": "Ataques Perigosos",
            "home": "18",
            "away": "14"
        }
    ]
}